{"width":512,"imagePath":"game-prota_backup_tex.png","height":256,"name":"game-prota_backup","SubTexture":[{"width":129,"y":1,"height":147,"name":"elf/scarf","x":1},{"width":42,"y":131,"height":69,"name":"elf/right_foot","x":313},{"width":58,"y":150,"height":75,"name":"elf/left_foot","x":1},{"width":64,"y":129,"height":79,"name":"elf/body","x":132},{"width":82,"y":1,"height":181,"name":"elf/slash","x":397},{"frameHeight":143,"y":1,"frameX":-12,"width":133,"frameY":-4,"height":126,"name":"elf/Base_head","frameWidth":177,"x":132},{"width":60,"y":131,"height":67,"name":"elf/lanternbackglow","x":251},{"width":36,"y":202,"height":36,"name":"elf/orb","x":428},{"width":35,"y":131,"height":64,"name":"elf/lantern","x":357},{"width":51,"y":129,"height":95,"name":"elf/right_arm_default","x":198},{"frameHeight":46,"y":200,"frameX":0,"width":49,"frameY":-2,"height":36,"name":"elf/left_arm_alt","frameWidth":53,"x":251},{"frameHeight":28,"y":227,"frameX":0,"width":22,"frameY":-2,"height":24,"name":"elf/left_arm_default","frameWidth":29,"x":1},{"width":128,"y":1,"height":128,"name":"elf/eyes","x":267},{"width":32,"y":184,"height":50,"name":"elf/hurt_expression","x":394},{"width":70,"y":210,"height":25,"name":"elf/brow","x":116},{"width":53,"y":150,"height":80,"name":"elf/bangs","x":61}]}